rz_ci_robot_framework/__init__.py
rz_ci_robot_framework/cli.py
rz_ci_robot_framework/version.py
rz_ci_robot_framework/common/__init__.py
rz_ci_robot_framework/common/board_config.py
rz_ci_robot_framework/libraries/PrintTextLibrary.py
rz_ci_robot_framework/libraries/__init__.py
rz_ci_robot_framework-1.0.1.dist-info/licenses/LICENSE
rz_ci_robot_framework-1.0.1.dist-info/METADATA
rz_ci_robot_framework-1.0.1.dist-info/WHEEL
rz_ci_robot_framework-1.0.1.dist-info/entry_points.txt
rz_ci_robot_framework-1.0.1.dist-info/top_level.txt
rz_ci_robot_framework-1.0.1.dist-info/RECORD
