Metadata-Version: 2.4
Name: rz-ci-robot-framework
Version: 1.0.1
Summary: Robot Framework-based testing framework for Renesas RZ boards
Home-page: https://github.com/renesas/rz-ci-robot-framework
Author: RZ-CI Team
Author-email: RZ-CI Team <rz-ci@renesas.com>
License-Expression: MIT
Project-URL: Homepage, https://github.com/renesas/rz-ci-robot-framework
Project-URL: Documentation, https://github.com/renesas/rz-ci-robot-framework/wiki
Project-URL: Repository, https://github.com/renesas/rz-ci-robot-framework
Project-URL: Issues, https://github.com/renesas/rz-ci-robot-framework/issues
Keywords: robot,framework,testing,renesas,rz,embedded,hardware
Classifier: Development Status :: 4 - Beta
Classifier: Intended Audience :: Developers
Classifier: Programming Language :: Python :: 3
Classifier: Programming Language :: Python :: 3.8
Classifier: Programming Language :: Python :: 3.9
Classifier: Programming Language :: Python :: 3.10
Classifier: Programming Language :: Python :: 3.11
Classifier: Topic :: Software Development :: Testing
Classifier: Framework :: Robot Framework
Requires-Python: >=3.8
License-File: LICENSE
Requires-Dist: robotframework<7.0.0,>=6.0.0
Requires-Dist: robotframework-seriallibrary>=0.3.1
Requires-Dist: robotframework-sshlibrary>=3.8.0
Requires-Dist: pyserial>=3.5
Requires-Dist: PyYAML>=6.0
Requires-Dist: python-dateutil>=2.8.0
Requires-Dist: pytz>=2023.3
Provides-Extra: docs
Requires-Dist: sphinx>=4.0.0; extra == "docs"
Requires-Dist: sphinx-rtd-theme>=1.2.0; extra == "docs"
Provides-Extra: testing
Requires-Dist: robotframework-metrics>=3.3.0; extra == "testing"
Requires-Dist: robotframework-pabot>=2.16.0; extra == "testing"
Dynamic: author
Dynamic: home-page
Dynamic: license-file
Dynamic: requires-python
